sphinx_minecraft-1.0.5.dist-info/METADATA
sphinx_minecraft-1.0.5.dist-info/WHEEL
sphinx_minecraft-1.0.5.dist-info/entry_points.txt
sphinx_minecraft-1.0.5.dist-info/licenses/LICENSE
sphinx_minecraft/__init__.py
sphinx_minecraft/icons/mcdir/audio.svg
sphinx_minecraft/icons/mcdir/file.svg
sphinx_minecraft/icons/mcdir/folder.svg
sphinx_minecraft/icons/mcdir/image.svg
sphinx_minecraft/icons/mcdir/json.svg
sphinx_minecraft/icons/mcdir/mcfunction.svg
sphinx_minecraft/icons/mcdir/mcmeta.svg
sphinx_minecraft/icons/mcdir/nbt.svg
sphinx_minecraft/icons/mcdir/yml.svg
sphinx_minecraft/icons/nbt/any.svg
sphinx_minecraft/icons/nbt/bool.svg
sphinx_minecraft/icons/nbt/byte-array.svg
sphinx_minecraft/icons/nbt/byte.svg
sphinx_minecraft/icons/nbt/compound.svg
sphinx_minecraft/icons/nbt/double.svg
sphinx_minecraft/icons/nbt/float.svg
sphinx_minecraft/icons/nbt/int-array.svg
sphinx_minecraft/icons/nbt/int.svg
sphinx_minecraft/icons/nbt/list.svg
sphinx_minecraft/icons/nbt/long-array.svg
sphinx_minecraft/icons/nbt/long.svg
sphinx_minecraft/icons/nbt/number.svg
sphinx_minecraft/icons/nbt/short.svg
sphinx_minecraft/icons/nbt/string.svg
sphinx_minecraft-1.0.5.dist-info/RECORD
