Metadata-Version: 2.1
Name: sphinx-minecraft
Version: 1.0.5
Summary: Add different Minecraft-oriented components to Sphinx.
Author-Email: theogiraudet <theo.giraudet@altearn.xyz>, Aksiome <maxime.calmon@altearn.xyz>
License: MPL-2.0
Classifier: Intended Audience :: Developers
Classifier: Framework :: Sphinx :: Extension
Classifier: License :: OSI Approved :: Mozilla Public License 2.0 (MPL 2.0)
Classifier: Programming Language :: Python :: 3.11
Project-URL: Repository, https://github.com/Gunivers/Sphinx-Minecraft/tree/main
Project-URL: Issues, https://github.com/Gunivers/Sphinx-Minecraft/issues
Requires-Python: >=3.11
Requires-Dist: sphinx
Requires-Dist: sphinx-treeview==1.1.1
Provides-Extra: docs
Requires-Dist: myst-parser; extra == "docs"
Requires-Dist: furo; extra == "docs"
